[
  {
    "id": "p-843833",
    "offset": 0,
    "text": "**Vishnu Smriti 25**"
  },
  {
    "id": "p-ad271e",
    "offset": 22,
    "text": "Now, the duties of women. // Vi_25.1 //"
  },
  {
    "id": "p-08c81d",
    "offset": 63,
    "text": "To follow the same vows as her husband. // Vi_25.2 //"
  },
  {
    "id": "p-623ff1",
    "offset": 118,
    "text": "To honor her mother-in-law, father-in-law, preceptor, deities, and guests. // Vi_25.3 //"
  },
  {
    "id": "p-2216f8",
    "offset": 208,
    "text": "To keep her household utensils well-ordered. // Vi_25.4 //"
  },
  {
    "id": "p-b43385",
    "offset": 268,
    "text": "Not to be open-handed. // Vi_25.5 //"
  },
  {
    "id": "p-a341f1",
    "offset": 306,
    "text": "To keep her vessels well-guarded. // Vi_25.6 //"
  },
  {
    "id": "p-c9f659",
    "offset": 355,
    "text": "Not to be fond of black magic. // Vi_25.7 //"
  },
  {
    "id": "p-a820e7",
    "offset": 401,
    "text": "To be devoted to auspicious practices. // Vi_25.8 //"
  },
  {
    "id": "p-a78e7d",
    "offset": 455,
    "text": "When her husband is away, not to adorn herself. // Vi_25.9 //"
  },
  {
    "id": "p-6f4ded",
    "offset": 518,
    "text": "Not to go to others' houses. // Vi_25.10 //"
  },
  {
    "id": "p-cdc348",
    "offset": 563,
    "text": "Not to stand at the door or in windows. // Vi_25.11 //"
  },
  {
    "id": "p-1c459e",
    "offset": 619,
    "text": "Not to be independent in any act. // Vi_25.12 //"
  },
  {
    "id": "p-19ce4e",
    "offset": 669,
    "text": "To be dependent on her father, husband, or son, in childhood, youth, and old age. // Vi_25.13 //"
  },
  {
    "id": "p-87f023",
    "offset": 767,
    "text": "When her husband is dead, to practice chastity or to ascend the funeral pyre after him. // Vi_25.14 //"
  },
  {
    "id": "p-dcb8f8",
    "offset": 871,
    "text": "For women there is no separate sacrifice, no vow, nor any fast;\n The husband whom she serves, by that she is glorified in heaven. || Vi_25.15 ||"
  },
  {
    "id": "p-cf077c",
    "offset": 1017,
    "text": "The woman who, while her husband is alive, undertakes a vow of fasting,\n She takes away her husband's life and goes to hell. || Vi_25.16 ||"
  },
  {
    "id": "p-ca9662",
    "offset": 1158,
    "text": "A virtuous woman who, after her husband's death, remains established in chastity,\n Goes to heaven, even if she is sonless, like those who are celibate students. || Vi_25.17 ||"
  }
]