[
  {
    "id": "p-f03c5a",
    "offset": 0,
    "text": "Arz-e naaz-e shokhi-e dandaan baraaye khanda hai\nDaawa-e jamiyyat-e ahbaab jaa-e khanda hai"
  },
  {
    "id": "p-b5f364",
    "offset": 93,
    "text": "Hai adam mein ghuncha mehv-e ibrat-e anjaam-e gul\nYak jahaan zaanu ta'ammul dar qafa-e khanda hai"
  },
  {
    "id": "p-eaf8e7",
    "offset": 192,
    "text": "Kulfat-e afsurdagi ko aish-e betaabi haraam\nWarna dandaan dar dil afshurdan binaa-e khanda hai"
  },
  {
    "id": "p-3fe07c",
    "offset": 288,
    "text": "Shorish-e baatin ke hain ahbaab munkir warna yaan\nDil muheet-e girya o lab aashna-e khanda hai"
  },
  {
    "id": "p-26e4cc",
    "offset": 384,
    "text": "Khud-faroshi haaye hasti bas-ki jaa-e khanda hai\nHar shikast-e qeemat-e dil mein sadaa-e khanda hai"
  },
  {
    "id": "p-71ec6a",
    "offset": 485,
    "text": "Naqsh-e ibrat dar nazar ya naqd-e ishrat dar bisaat\nDo jahaan vus'at ba-qadr-e yak fazaa-e khanda hai"
  },
  {
    "id": "p-b370da",
    "offset": 588,
    "text": "Jaa-e istehza hai ishrat-koshi-e hasti, Asad\nSubh o shabnam fursat-e nashv-o-numaa-e khanda hai"
  }
]