{
  "work_slug": "unknown-old-english-elegies-d5fe9e",
  "work_title": "Old English Elegies",
  "chapter_number": 9,
  "chapter_title": "Resignation",
  "chapter_slug": "09-resignation",
  "layout": "prose",
  "layouts_in_variants": [
    "verse",
    "prose"
  ],
  "default_variant": "translation.md",
  "variants": [
    {
      "file": "original.md",
      "content_type": "original",
      "variant_id": "478e21bd-e760-4bfa-9170-3cce118c0a56",
      "language": "old_english",
      "source_language": "old_english",
      "script": "latin",
      "word_count": 799,
      "paragraph_count": 5,
      "has_image": false,
      "source_url": "https://sacred-texts.com/neu/ascp/a03_25.htm"
    },
    {
      "file": "translation.md",
      "content_type": "translation",
      "variant_id": "7dab0bce-1446-4e94-a67c-1fb318f38e3b",
      "language": "english",
      "source_language": "old_english",
      "script": "latin",
      "word_count": 890,
      "paragraph_count": 1,
      "has_image": false,
      "source_url": null
    },
    {
      "file": "translation-2.md",
      "content_type": "translation",
      "variant_id": "cabd809d-1db9-41e3-a6c5-1776b9335c1d",
      "language": "english",
      "source_language": "old_english",
      "script": "latin",
      "word_count": 775,
      "paragraph_count": 5,
      "has_image": false,
      "source_url": "https://sacred-texts.com/neu/ascp/a03_25.htm"
    }
  ]
}