[
  {
    "id": "p-f6202f",
    "offset": 0,
    "text": "Kabhi neiki bhi us ke jee mein gar aa jaaye hai mujh se\nJafaayein kar ke apni yaad sharma jaaye hai mujh se"
  },
  {
    "id": "p-a4eb27",
    "offset": 109,
    "text": "Khudaaya jazba-e-dil ki magar taseer ulti hai\nKe jitna kheenchta hoon aur khinchta jaaye hai mujh se"
  },
  {
    "id": "p-ebe407",
    "offset": 211,
    "text": "Woh bad-khoo aur meri daastaan-e-ishq toolaani\nIbaarat mukhtasar qaasid bhi ghabra jaaye hai mujh se"
  },
  {
    "id": "p-793024",
    "offset": 313,
    "text": "Idhar woh bad-gumaani hai idhar yeh na-tawaani hai\nNa poochha jaaye hai us se na bola jaaye hai mujh se"
  },
  {
    "id": "p-2d8915",
    "offset": 418,
    "text": "Sambhalne de mujhe ae na-umeedi kya qayamat hai\nKe daaman-e-khayal-e-yaar chhoota jaaye hai mujh se"
  },
  {
    "id": "p-c881e5",
    "offset": 519,
    "text": "Takalluf bar-taraf nazzargi mein bhi sahi lekin\nWoh dekha jaaye kab yeh zulm dekha jaaye hai mujh se"
  },
  {
    "id": "p-23c578",
    "offset": 621,
    "text": "Huye hain paaon hi pehle nabard-e-ishq mein zakhmi\nNa bhaaga jaaye hai mujh se na thehra jaaye hai mujh se"
  },
  {
    "id": "p-46ff08",
    "offset": 729,
    "text": "Qayamat hai ke hove muddai ka hum-safar Ghalib\nWoh kaafir jo Khuda ko bhi na saunpa jaaye hai mujh se"
  }
]