[
  {
    "id": "p-ff298a",
    "offset": 0,
    "text": "تم اپنے شکوے کی باتیں نہ کھود کھود کے پوچھو\r\nحذر کرو مرے دل سے کہ اس میں آگ دبی ہے"
  },
  {
    "id": "p-f37753",
    "offset": 84,
    "text": "دلا یہ درد_و_الم بھی تو مغتنم ہے کہ آخر\r\nنہ گریۂ_سحری ہے نہ آہ_نیم_شبی ہے"
  },
  {
    "id": "p-3119b8",
    "offset": 159,
    "text": "نظر بہ_نقص_گدایاں کمال_بے_ادبی ہے\r\nکہ خار_خشک کو بھی دعواۓ_چمن_نسبی ہے"
  },
  {
    "id": "p-31bb40",
    "offset": 232,
    "text": "ہوا وصال سے شوق_دل_حریص زیادہ\r\nلب_قدح پہ کف_بادہ جوش_تشنہ_لبی ہے"
  },
  {
    "id": "p-33912b",
    "offset": 298,
    "text": "خوشا وہ دل کہ سراپا طلسم_بے_خبری ہو\r\nجنون و یاس و الم رزق_مدعا_طلبی ہے"
  },
  {
    "id": "p-217a39",
    "offset": 370,
    "text": "چمن میں کس کے یہ برہم ہوئی ہے بزم_تماشا\r\nکہ برگ برگ_سمن شیشہ ریزۂ_حلبی ہے"
  },
  {
    "id": "p-02c2f0",
    "offset": 446,
    "text": "امام_ظاہر_و_باطن امیر_صورت_و_معنی\r\nعلیؔ ولی اسداللہ جانشین_نبی ہے"
  }
]