[
  {
    "id": "p-032160",
    "offset": 0,
    "text": "Rukh-e-nigaar se hai soz-e-jaavedaani-e-shama\nHui hai aatish-e-gul aab-e-zindagaani-e-shama"
  },
  {
    "id": "p-06dd8d",
    "offset": 93,
    "text": "Zubaan-e-ahl-e-zubaan mein hai marg-e-khaamoshi\nYeh baat bazm mein raushan hui zubaani-e-shama"
  },
  {
    "id": "p-e23450",
    "offset": 189,
    "text": "Kare hai sarf ba-imaa-e-shola qissa tamaam\nBa-tarz-e-ahl-e-fana hai fasaana-khwaani-e-shama"
  },
  {
    "id": "p-9c69a3",
    "offset": 282,
    "text": "Gham usko hasrat-e-parwaana ka hai aye sholay\nTere larazne se zaahir hai na-tawaani-e-shama"
  },
  {
    "id": "p-a7f6d4",
    "offset": 375,
    "text": "Tere khayaal se rooh ehtizaaz karti hai\nBa-jalva-rezi-e-baad o ba-par-fishaani-e-shama"
  },
  {
    "id": "p-155f2e",
    "offset": 463,
    "text": "Nishaat-e-daagh-e-gham-e-ishq ki bahaar na poochh\nShaguftagi hai shaheed-e-gul-e-khizaani-e-shama"
  },
  {
    "id": "p-044c2c",
    "offset": 562,
    "text": "Jale hai dekh ke baalin-e-yaar par mujh ko\nNa kyon ho dil pe mere daagh-e-bad-gumaani-e-shama"
  }
]